BlizzGameData/Battlenet.py
BlizzGameData/GameData.py
BlizzGameData/__init__.py
BlizzGameData/loggerConfig.py
BlizzGameData/api_resources/AuctionHouse.py
BlizzGameData/api_resources/ConnectedRealm.py
BlizzGameData/api_resources/Realm.py
BlizzGameData/api_resources/Resource.py
BlizzGameData/api_resources/__init__.py
BlizzGameData/oauth_flows/ClientCredentials.py
BlizzGameData/oauth_flows/__init__.py
BlizzGameData-0.0.7.dist-info/LICENSE
BlizzGameData-0.0.7.dist-info/METADATA
BlizzGameData-0.0.7.dist-info/WHEEL
BlizzGameData-0.0.7.dist-info/top_level.txt
BlizzGameData-0.0.7.dist-info/RECORD
